README.md
setup.cfg
setup.py
noolite_api/__init__.py
noolite_api/const.py
noolite_api/nl_base.py
noolite_api/nl_ethernet.py
noolite_api/nl_serial.py
noolite_api/typing.py
noolite_api.egg-info/PKG-INFO
noolite_api.egg-info/SOURCES.txt
noolite_api.egg-info/dependency_links.txt
noolite_api.egg-info/requires.txt
noolite_api.egg-info/top_level.txt