Metadata-Version: 1.0
Name: noolite-api
Version: 0.1.6
Summary: Noolite communication
Home-page: https://github.com/andvikt/noolite_serial
Author: andrewgermanovich
Author-email: andvikt@gmail.com
License: BSD
Platform: UNKNOWN
